mutalyzer_hgvs_parser/__init__.py
mutalyzer_hgvs_parser/cli.py
mutalyzer_hgvs_parser/convert.py
mutalyzer_hgvs_parser/exceptions.py
mutalyzer_hgvs_parser/hgvs_parser.py
mutalyzer_hgvs_parser/util.py
mutalyzer_hgvs_parser/ebnf/common.g
mutalyzer_hgvs_parser/ebnf/description.g
mutalyzer_hgvs_parser/ebnf/dna.g
mutalyzer_hgvs_parser/ebnf/hgvs_mutalyzer_3.g
mutalyzer_hgvs_parser/ebnf/protein.g
mutalyzer_hgvs_parser/ebnf/reference.g
mutalyzer_hgvs_parser/ebnf/top.g
mutalyzer_hgvs_parser-0.3.9.dist-info/licenses/LICENSE
mutalyzer_hgvs_parser-0.3.9.dist-info/METADATA
mutalyzer_hgvs_parser-0.3.9.dist-info/WHEEL
mutalyzer_hgvs_parser-0.3.9.dist-info/entry_points.txt
mutalyzer_hgvs_parser-0.3.9.dist-info/top_level.txt
mutalyzer_hgvs_parser-0.3.9.dist-info/RECORD
