Metadata-Version: 2.4
Name: mutalyzer_hgvs_parser
Version: 0.3.9
Summary: Mutalyzer HGVS variant description parser.
Home-page: https://github.com/mutalyzer/hgvs-parser
Author: Mihai Lefter
Author-email: M.Lefter@lumc.nl
License: MIT
Keywords: Mutalyzer,HGVS,description,parser,genomic
Classifier: Intended Audience :: Science/Research
Classifier: Intended Audience :: Developers
Classifier: Operating System :: OS Independent
Classifier: Programming Language :: Python :: 3
Classifier: Topic :: Scientific/Engineering :: Bio-Informatics
Classifier: Programming Language :: Python :: 3.8
Classifier: Programming Language :: Python :: 3.9
Classifier: Programming Language :: Python :: 3.10
Classifier: Programming Language :: Python :: 3.11
Classifier: Programming Language :: Python :: 3.12
Classifier: Programming Language :: Python :: 3.13
Requires-Python: >=3.8
License-File: LICENSE
Requires-Dist: lark>=1.0.0
Provides-Extra: dev
Requires-Dist: coverage; extra == "dev"
Requires-Dist: flake8; extra == "dev"
Requires-Dist: pytest; extra == "dev"
Requires-Dist: setuptools; extra == "dev"
Requires-Dist: twine; extra == "dev"
Dynamic: license-file
